Metadata-Version: 1.1
Name: cerberus-collections
Version: 1.2016.9a1
Summary: Extensions for cerberus, a lightweight and extensible data validation library for Python
Home-page: https://github.com/funkyfuture/cerberus-collections
Author: Frank Sachsenheim
Author-email: funkyfuture@riseup.net
License: ISC
Keywords: validation,schema,xml
Platform: any
Classifier: Development Status :: 3 - Alpha
Classifier: Intended Audience :: Developers
Classifier: License :: OSI Approved :: ISC License (ISCL)
Classifier: Operating System :: OS Independent
Classifier: Programming Language :: Python
Classifier: Programming Language :: Python :: 3
Classifier: Programming Language :: Python :: 3.4
Classifier: Programming Language :: Python :: 3.5
Classifier: Programming Language :: Python :: Implementation :: CPython
Classifier: Programming Language :: Python :: Implementation :: PyPy
